emon_tools/__init__.py
emon_tools/core/__init__.py
emon_tools/core/utils.py
emon_tools/emon_api/__init__.py
emon_tools/emon_api/api_utils.py
emon_tools/emon_api/async_emon_api.py
emon_tools/emon_api/emon_api.py
emon_tools/emon_api/emon_api_core.py
emon_tools/emon_fina/__init__.py
emon_tools/emon_fina/emon_fina.py
emon_tools/emon_fina/fina_models.py
emon_tools/emon_fina/fina_plot.py
emon_tools/emon_fina/fina_reader.py
emon_tools/emon_fina/fina_services.py
emon_tools/emon_fina/fina_time_series.py
emon_tools/emon_fina/fina_utils.py
emon_tools/emonpy/__init__.py
emon_tools/emonpy/async_emonpy.py
emon_tools/emonpy/emonpy.py
emon_tools/emonpy/emonpy_core.py
emon_tools-0.3.1.dist-info/licenses/LICENSE
emon_tools-0.3.1.dist-info/METADATA
emon_tools-0.3.1.dist-info/WHEEL
emon_tools-0.3.1.dist-info/top_level.txt
emon_tools-0.3.1.dist-info/zip-safe
emon_tools-0.3.1.dist-info/RECORD
