Metadata-Version: 2.4
Name: emon-tools
Version: 0.3.1
Summary: A Python PHPFINA feeds and Api Tools to interact with EmonCms.
Home-page: https://github.com/vemonitor/emon_tools
Author: Eli Serra
Author-email: mano8@gmail.com
License: MIT
Keywords: EmonCms,Python,PhpFina,JsonApi
Classifier: Programming Language :: Python :: 3
Classifier: Operating System :: OS Independent
Requires-Python: >=3.10
License-File: LICENSE
Provides-Extra: test
Requires-Dist: pytest>=8.3.4; extra == "test"
Requires-Dist: pytest-cov>=6.0.0; extra == "test"
Requires-Dist: coverage>=7.6.9; extra == "test"
Requires-Dist: requests>=2.32.3; extra == "test"
Requires-Dist: aiohttp>=3.8.1; extra == "test"
Requires-Dist: pytest-aiohttp>=1.0.5; extra == "test"
Requires-Dist: pandas>=2.2.3; extra == "test"
Requires-Dist: matplotlib>=3.9.3; extra == "test"
Provides-Extra: notebook
Requires-Dist: jupyter>=1.0.0; extra == "notebook"
Requires-Dist: pandas>=2.2.3; extra == "notebook"
Requires-Dist: matplotlib>=3.9.3; extra == "notebook"
Provides-Extra: time-series
Requires-Dist: pandas>=2.2.3; extra == "time-series"
Provides-Extra: plot
Requires-Dist: pandas>=2.2.3; extra == "plot"
Requires-Dist: matplotlib>=3.9.3; extra == "plot"
Provides-Extra: fina
Requires-Dist: numpy>=2.2.0; extra == "fina"
Provides-Extra: api
Requires-Dist: requests>=2.32.3; extra == "api"
Requires-Dist: simplejson>=3.19.3; extra == "api"
Provides-Extra: async-api
Requires-Dist: aiohttp>=3.8.1; extra == "async-api"
Requires-Dist: simplejson>=3.19.3; extra == "async-api"
Provides-Extra: all
Requires-Dist: jupyter>=1.0.0; extra == "all"
Requires-Dist: numpy>=2.2.0; extra == "all"
Requires-Dist: aiohttp>=3.8.1; extra == "all"
Requires-Dist: requests>=2.32.3; extra == "all"
Requires-Dist: simplejson>=3.19.3; extra == "all"
Requires-Dist: pandas>=2.2.3; extra == "all"
Requires-Dist: matplotlib>=3.9.3; extra == "all"
Requires-Dist: pydantic>=2.10.6; extra == "all"
Requires-Dist: pydantic-settings>=2.7.1; extra == "all"
Dynamic: license-file
